botrun_embeddings.py
botrun_embeddings-1.1.1.dist-info/METADATA
botrun_embeddings-1.1.1.dist-info/WHEEL
botrun_embeddings-1.1.1.dist-info/entry_points.txt
botrun_embeddings-1.1.1.dist-info/top_level.txt
botrun_embeddings-1.1.1.dist-info/RECORD
