Metadata-Version: 2.1
Name: botrun-embeddings
Version: 1.1.1
Requires-Dist: torch
Requires-Dist: sentence-transformers
Requires-Dist: scikit-learn
